pyniche/__init__.py
pyniche/device.py
pyniche/evaluate.py
pyniche/optimizer.py
pyniche/show.py
pyniche/trainer.py
pyniche/data/__init__.py
pyniche/data/base.py
pyniche/data/bbox.py
pyniche/data/download.py
pyniche/data/coco/API.py
pyniche/data/coco/__init__.py
pyniche/data/coco/detr.py
pyniche/data/huggingface/__init__.py
pyniche/data/huggingface/detection.py
pyniche/data/huggingface/regression.py
pyniche/data/yolo/API.py
pyniche/data/yolo/__init__.py
pyniche/models/__init__.py
pyniche/models/base.py
pyniche/models/mlp.py
pyniche/models/optimization.py
pyniche/models/detection/__init__.py
pyniche/models/detection/detr.py
pyniche/models/detection/yolo.py
pyniche/models/regression/__init__.py
pyniche/models/regression/deit.py
pyniche/models/regression/vit.py
pyniche/utils/__init__.py
pyniche/utils/optuna.py
pyniche/visualization/__init__.py
pyniche/visualization/coco.py
pyniche/visualization/supervision.py
pyniche-0.0.18.dist-info/LICENSE
pyniche-0.0.18.dist-info/METADATA
pyniche-0.0.18.dist-info/WHEEL
pyniche-0.0.18.dist-info/entry_points.txt
pyniche-0.0.18.dist-info/top_level.txt
pyniche-0.0.18.dist-info/RECORD
