Metadata-Version: 2.1
Name: pyniche
Version: 0.0.18
Summary: An AI Library for Niche Squad
Home-page: https://github.com/Niche-Squad/pyniche
Author: James Chen
Author-email: niche@vt.edu
License-File: LICENSE
Requires-Dist: pandas
Requires-Dist: numpy
Requires-Dist: scipy
Requires-Dist: scikit-learn
Requires-Dist: datasets
Requires-Dist: supervision
Requires-Dist: optuna
Requires-Dist: albumentations
Requires-Dist: ultralytics
Requires-Dist: lightning
Requires-Dist: transformers
Requires-Dist: torch
Requires-Dist: torchvision
Requires-Dist: torchaudio
Requires-Dist: seaborn
Requires-Dist: matplotlib
